MANIFEST.in
README.md
setup.cfg
setup.py
examples/__init__.py
examples/decision_vs_research.py
examples/outsourcing.py
examples/print.py
examples/stpetersburg.py
examples/stpetersburg_w_bankroll.py
petersburg/__init__.py
petersburg/edges.py
petersburg/graph.py
petersburg/nodes.py
petersburg.egg-info/PKG-INFO
petersburg.egg-info/SOURCES.txt
petersburg.egg-info/dependency_links.txt
petersburg.egg-info/top_level.txt