Metadata-Version: 1.1
Name: petersburg
Version: 0.0.1
Summary: A simple framework for analyzing probabalistic decision processes as directed graphs
Home-page: https://github.com/wdm0006/petersburg
Author: Will McGinnis
Author-email: will@pedalwrencher.com
License: BSD
Download-URL: https://github.com/wdm0006/petersburg/tarball/0.0.1
Platform: UNKNOWN
Classifier: Development Status :: 3 - Alpha
Classifier: Intended Audience :: Developers
Classifier: Programming Language :: Python :: 3
